[
    {
        "name": "creation_date",
        "type": "DATETIME",
        "mode": "NULLABLE"
    },
    {
        "name": "id",
        "type": "STRING",
        "mode": "NULLABLE"
    },
    {
        "name": "ingestion_date",
        "type": "DATETIME",
        "mode": "NULLABLE"
    },
    {
        "name": "last_update",
        "type": "DATETIME",
        "mode": "NULLABLE"
    },
    {
        "name": "sales_channel",
        "type": "STRING",
        "mode": "NULLABLE"
    },
    {
        "name": "state",
        "type": "STRING",
        "mode": "NULLABLE"
    },
    {
        "name": "customer",
        "type": "RECORD",
        "mode": "NULLABLE",
        "fields": [
            {
                "name": "email",
                "type": "STRING",
                "mode": "NULLABLE"
            },
            {
                "name": "first_name",
                "type": "STRING",
                "mode": "NULLABLE"
            },
            {
                "name": "id",
                "type": "STRING",
                "mode": "NULLABLE"
            },
            {
                "name": "last_name",
                "type": "STRING",
                "mode": "NULLABLE"
            },
            {
                "name": "phone_number",
                "type": "STRING",
                "mode": "NULLABLE"
            },
            {
                "name": "title",
                "type": "STRING",
                "mode": "NULLABLE"
            }
        ]
    },
    {
        "name": "delivery",
        "type": "RECORD",
        "mode": "NULLABLE",
        "fields": [
            {
                "name": "address",
                "type": "STRING",
                "mode": "NULLABLE"
            },
            {
                "name": "city",
                "type": "STRING",
                "mode": "NULLABLE"
            },
            {
                "name": "country",
                "type": "STRING",
                "mode": "NULLABLE"
            },
            {
                "name": "email",
                "type": "STRING",
                "mode": "NULLABLE"
            },
            {
                "name": "first_name",
                "type": "STRING",
                "mode": "NULLABLE"
            },
            {
                "name": "last_name",
                "type": "STRING",
                "mode": "NULLABLE"
            },
            {
                "name": "phone_number",
                "type": "STRING",
                "mode": "NULLABLE"
            },
            {
                "name": "relay_point",
                "type": "STRING",
                "mode": "NULLABLE"
            },
            {
                "name": "title",
                "type": "STRING",
                "mode": "NULLABLE"
            },
            {
                "name": "type",
                "type": "STRING",
                "mode": "NULLABLE"
            },
            {
                "name": "zipcode",
                "type": "STRING",
                "mode": "NULLABLE"
            },
            {
                "name": "store_id",
                "type": "STRING",
                "mode": "NULLABLE"
            }
        ]
    },
    {
        "name": "information",
        "type": "RECORD",
        "mode": "NULLABLE",
        "fields": [
            {
                "name": "delivery_mode",
                "type": "STRING",
                "mode": "NULLABLE"
            },
            {
                "name": "delivery_pickup_id",
                "type": "STRING",
                "mode": "NULLABLE"
            },
            {
                "name": "message",
                "type": "STRING",
                "mode": "NULLABLE"
            }
        ]
    },
    {
        "name": "items",
        "type": "RECORD",
        "mode": "REPEATED",
        "fields": [
            {
                "name": "id",
                "type": "STRING",
                "mode": "NULLABLE"
            },
            {
                "name": "pricing",
                "type": "RECORD",
                "mode": "NULLABLE",
                "fields": [
                    {
                        "name": "currency",
                        "type": "STRING",
                        "mode": "NULLABLE"
                    },
                    {
                        "name": "original_price",
                        "type": "NUMERIC",
                        "mode": "NULLABLE"
                    },
                    {
                        "name": "price",
                        "type": "NUMERIC",
                        "mode": "NULLABLE"
                    }
                ]
            },
            {
                "name": "product_id",
                "type": "STRING",
                "mode": "NULLABLE"
            },
            {
                "name": "quantity",
                "type": "INTEGER",
                "mode": "NULLABLE"
            },
            {
                "name": "state",
                "type": "STRING",
                "mode": "NULLABLE"
            }
        ]
    },
    {
        "name": "parcels",
        "type": "RECORD",
        "mode": "REPEATED",
        "fields": [
            {
                "name": "carrier",
                "type": "RECORD",
                "mode": "NULLABLE",
                "fields": [
                    {
                        "name": "delivery_mode",
                        "type": "STRING",
                        "mode": "NULLABLE"
                    },
                    {
                        "name": "name",
                        "type": "STRING",
                        "mode": "NULLABLE"
                    },
                    {
                        "name": "option",
                        "type": "STRING",
                        "mode": "NULLABLE"
                    }
                ]
            },
            {
                "name": "date",
                "type": "DATETIME",
                "mode": "NULLABLE"
            },
            {
                "name": "destination",
                "type": "RECORD",
                "mode": "NULLABLE",
                "fields": [
                    {
                        "name": "address",
                        "type": "STRING",
                        "mode": "NULLABLE"
                    },
                    {
                        "name": "city",
                        "type": "STRING",
                        "mode": "NULLABLE"
                    },
                    {
                        "name": "country",
                        "type": "STRING",
                        "mode": "NULLABLE"
                    },
                    {
                        "name": "email",
                        "type": "STRING",
                        "mode": "NULLABLE"
                    },
                    {
                        "name": "first_name",
                        "type": "STRING",
                        "mode": "NULLABLE"
                    },
                    {
                        "name": "last_name",
                        "type": "STRING",
                        "mode": "NULLABLE"
                    },
                    {
                        "name": "phone_number",
                        "type": "STRING",
                        "mode": "NULLABLE"
                    },
                    {
                        "name": "title",
                        "type": "STRING",
                        "mode": "NULLABLE"
                    },
                    {
                        "name": "zipcode",
                        "type": "STRING",
                        "mode": "NULLABLE"
                    },
                    {
                        "name": "store_id",
                        "type": "STRING",
                        "mode": "NULLABLE"
                    }
                ]
            },
            {
                "name": "origin_endpoint_id",
                "type": "STRING",
                "mode": "NULLABLE"
            },            
            {
                "name": "items",
                "type": "RECORD",
                "mode": "REPEATED",
                "fields": [
                    {
                        "name": "id",
                        "type": "STRING",
                        "mode": "NULLABLE"
                    },
                    {
                        "name": "pricing",
                        "type": "RECORD",
                        "mode": "NULLABLE",
                        "fields": [
                            {
                                "name": "currency",
                                "type": "STRING",
                                "mode": "NULLABLE"
                            },
                            {
                                "name": "original_price",
                                "type": "NUMERIC",
                                "mode": "NULLABLE"
                            },
                            {
                                "name": "price",
                                "type": "NUMERIC",
                                "mode": "NULLABLE"
                            }
                        ]
                    },
                    {
                        "name": "product_id",
                        "type": "STRING",
                        "mode": "NULLABLE"
                    },
                    {
                        "name": "quantity",
                        "type": "INTEGER",
                        "mode": "NULLABLE"
                    },
                    {
                        "name": "state",
                        "type": "STRING",
                        "mode": "NULLABLE"
                    }
                ]
            },
            {
                "name": "last_update",
                "type": "DATETIME",
                "mode": "NULLABLE"
            },
            {
                "name": "shipment",
                "type": "RECORD",
                "mode": "NULLABLE",
                "fields": [
                    {
                        "name": "external_carrier",
                        "type": "STRING",
                        "mode": "NULLABLE"
                    },
                    {
                        "name": "id",
                        "type": "STRING",
                        "mode": "NULLABLE"
                    },
                    {
                        "name": "tracking_code",
                        "type": "STRING",
                        "mode": "NULLABLE"
                    },
                    {
                        "name": "tracking_link",
                        "type": "STRING",
                        "mode": "NULLABLE"
                    },
                    {
                        "name": "transporter",
                        "type": "STRING",
                        "mode": "NULLABLE"
                    }
                ]
            },
            {
                "name": "state",
                "type": "STRING",
                "mode": "NULLABLE"
            }
        ]
    },
    {
        "name": "payment",
        "type": "RECORD",
        "mode": "NULLABLE",
        "fields": [
            {
                "name": "contact",
                "type": "RECORD",
                "mode": "NULLABLE",
                "fields": [
                    {
                        "name": "address",
                        "type": "STRING",
                        "mode": "NULLABLE"
                    },
                    {
                        "name": "city",
                        "type": "STRING",
                        "mode": "NULLABLE"
                    },
                    {
                        "name": "country",
                        "type": "STRING",
                        "mode": "NULLABLE"
                    },
                    {
                        "name": "email",
                        "type": "STRING",
                        "mode": "NULLABLE"
                    },
                    {
                        "name": "first_name",
                        "type": "STRING",
                        "mode": "NULLABLE"
                    },
                    {
                        "name": "last_name",
                        "type": "STRING",
                        "mode": "NULLABLE"
                    },
                    {
                        "name": "phone_number",
                        "type": "STRING",
                        "mode": "NULLABLE"
                    },
                    {
                        "name": "title",
                        "type": "STRING",
                        "mode": "NULLABLE"
                    },
                    {
                        "name": "zipcode",
                        "type": "STRING",
                        "mode": "NULLABLE"
                    }
                ]
            },
            {
                "name": "currency",
                "type": "STRING",
                "mode": "NULLABLE"
            },
            {
                "name": "price",
                "type": "NUMERIC",
                "mode": "NULLABLE"
            }
        ]
    },
    {
        "name": "shipping_fees",
        "type": "STRING",
        "mode": "NULLABLE"
    }
]